{"2012":{"I":{"Italia":"1199"}},"2013":{"I":{"Italia":"1149"}},"2014":{"I":{"Italia":"1131"}},"2015":{"I":{"Italia":"1154"}},"2016":{"I":{"Italia":"1162"}},"2017":{"I":{"Italia":"1152"}},"2018":{"I":{"Italia":"1145"}},"2019":{"I":{"Italia":"1129"},"Z":{"Nord-ovest":"336","Nord-est":"261","Centro":"265","Sud":"186","Isole":"81"},"R":{"Valle d'Aosta \/ Vall\u00e9e d'Aoste":"1","Piemonte":"74","Liguria":"12","Lombardia":"249","Trentino Alto Adige \/ S\u00fcdtirol":"8","Friuli-Venezia Giulia":"13","Veneto":"140","Emilia-Romagna":"100","Umbria":"21","Lazio":"45","Toscana":"127","Abruzzo":"26","Campania":"83","Marche":"72","Puglia":"53","Basilicata":"2","Molise":"4","Sardegna":"9","Sicilia":"72","Calabria":"18","Provincia Autonoma Bolzano \/ Bozen":"1","Provincia Autonoma Trento":"7"},"P":{"Torino":"36","Vercelli":"4","Biella":"2","Verbano-Cusio-Ossola":"1","Novara":"11","Cuneo":"12","Asti":"4","Alessandria":"4","Valle d'Aosta \/ Vall\u00e9e d'Aoste":"1","Imperia":"2","Savona":"1","Genova":"8","La Spezia":"1","Varese":"23","Como":"20","Lecco":"11","Sondrio":"3","Milano":"60","Bergamo":"30","Brescia":"32","Pavia":"9","Lodi":"1","Cremona":"7","Mantova":"13","Bolzano \/ Bozen":"1","Trento":"7","Verona":"21","Vicenza":"27","Belluno":"1","Treviso":"49","Venezia":"8","Padova":"30","Rovigo":"4","Pordenone":"6","Udine":"5","Gorizia":"2","Piacenza":"4","Parma":"16","Reggio nell'Emilia":"19","Modena":"21","Bologna":"16","Ferrara":"5","Ravenna":"4","Forl\u00ec-Cesena":"13","Rimini":"2","Lucca":"30","Pistoia":"21","Firenze":"27","Prato":"6","Livorno":"3","Pisa":"12","Arezzo":"17","Siena":"9","Grosseto":"2","Perugia":"19","Terni":"2","Pesaro e Urbino":"20","Ancona":"18","Macerata":"18","Ascoli Piceno":"3","Viterbo":"2","Rieti":"2","Roma":"28","Latina":"6","Frosinone":"7","L'Aquila":"3","Teramo":"9","Pescara":"2","Chieti":"12","Isernia":"1","Campobasso":"3","Caserta":"11","Benevento":"3","Napoli":"49","Avellino":"1","Salerno":"19","Foggia":"6","Bari":"17","Taranto":"9","Brindisi":"1","Lecce":"10","Potenza":"1","Matera":"1","Cosenza":"7","Crotone":"1","Catanzaro":"4","Reggio di Calabria":"6","Trapani":"3","Palermo":"10","Messina":"4","Agrigento":"3","Caltanissetta":"3","Catania":"29","Ragusa":"13","Siracusa":"7","Sassari":"2","Cagliari":"2","Oristano":"1","Monza e della Brianza":"40","Fermo":"13","Barletta-Andria-Trani":"10","Sud Sardegna":"4"}},"2020":{"I":{"Italia":"1111"}}}