{"2012":{"Z":{"Centro":"76","Nord-est":"31","Nord-ovest":"53","Sud":"65","Isole":"14"},"I":{"Italia":"239"}},"2013":{"Z":{"Centro":"77","Nord-est":"31","Nord-ovest":"49","Sud":"61","Isole":"17"},"I":{"Italia":"235"}},"2014":{"Z":{"Centro":"73","Nord-est":"29","Nord-ovest":"49","Sud":"56","Isole":"16"},"I":{"Italia":"223"}},"2015":{"Z":{"Centro":"73","Nord-est":"30","Nord-ovest":"48","Sud":"57","Isole":"15"},"I":{"Italia":"223"}},"2016":{"Z":{"Centro":"70","Nord-est":"29","Nord-ovest":"48","Sud":"61","Isole":"19"},"I":{"Italia":"227"}},"2017":{"Z":{"Centro":"65","Nord-est":"27","Nord-ovest":"44","Sud":"59","Isole":"16"},"I":{"Italia":"211"}},"2018":{"Z":{"Centro":"62","Nord-est":"27","Nord-ovest":"44","Sud":"59","Isole":"15"},"I":{"Italia":"207"}},"2019":{"Z":{"Centro":"67","Nord-est":"25","Nord-ovest":"40","Sud":"58","Isole":"15"},"I":{"Italia":"205"},"R":{"Piemonte":"8","Liguria":"1","Lombardia":"31","Veneto":"16","Emilia-Romagna":"8","Friuli-Venezia Giulia":"1","Toscana":"54","Marche":"4","Abruzzo":"7","Lazio":"5","Umbria":"4","Campania":"17","Basilicata":"6","Calabria":"3","Puglia":"25","Sicilia":"14","Sardegna":"1"},"P":{"Torino":"3","Novara":"2","Cuneo":"2","Alessandria":"1","Genova":"1","Varese":"4","Como":"1","Lecco":"4","Sondrio":"2","Milano":"7","Bergamo":"3","Brescia":"2","Pavia":"1","Cremona":"4","Mantova":"1","Verona":"2","Vicenza":"4","Treviso":"2","Venezia":"2","Padova":"4","Rovigo":"2","Pordenone":"1","Bologna":"3","Ravenna":"3","Forl\u00ec-Cesena":"1","Rimini":"1","Massa-Carrara":"2","Lucca":"27","Pistoia":"13","Firenze":"5","Prato":"2","Livorno":"2","Pisa":"1","Arezzo":"2","Perugia":"4","Ancona":"2","Macerata":"1","Roma":"2","Latina":"1","Frosinone":"2","Teramo":"2","Pescara":"2","Chieti":"3","Caserta":"4","Napoli":"10","Salerno":"3","Foggia":"1","Bari":"14","Brindisi":"2","Lecce":"6","Potenza":"4","Matera":"2","Cosenza":"1","Catanzaro":"1","Reggio di Calabria":"1","Trapani":"2","Palermo":"3","Catania":"9","Sassari":"1","Monza e della Brianza":"2","Fermo":"1","Barletta-Andria-Trani":"2"}},"2020":{"Z":{"Centro":"68","Nord-est":"24","Nord-ovest":"42","Sud":"54","Isole":"13"},"I":{"Italia":"201"}}}