{"2012":{"I":{"Italia":"191"},"Z":{"Nord-est":"26","Sud":"82","Nord-ovest":"18","Centro":"30","Isole":"35"},"R":{"Emilia-Romagna":"10","Marche":"4","Campania":"33","Lazio":"14","Friuli-Venezia Giulia":"5","Lombardia":"9","Veneto":"11","Sicilia":"30","Puglia":"26","Liguria":"1","Abruzzo":"1","Calabria":"17","Sardegna":"5","Umbria":"4","Basilicata":"3","Toscana":"8","Piemonte":"8","Molise":"2"},"P":{"Treviso":"2","Bologna":"3","Foggia":"1","Como":"1","Piacenza":"1","Benevento":"2","Salerno":"10","Brindisi":"9","Catanzaro":"5","Vibo Valentia":"2","Reggio di Calabria":"8","Firenze":"2","Siena":"2","Perugia":"3","Ascoli Piceno":"1","Potenza":"2","Matera":"1","Genova":"1","Bergamo":"4","Pordenone":"1","Udine":"3","Ravenna":"1","Pisa":"1","Grosseto":"2","Roma":"8","Cosenza":"2","Catania":"3","Torino":"2","Cuneo":"2","Mantova":"1","Vicenza":"3","Reggio nell'Emilia":"1","Rimini":"1","Terni":"1","Pesaro e Urbino":"1","Ancona":"2","Latina":"4","Isernia":"2","Caserta":"8","Cagliari":"2","Brescia":"1","Padova":"6","Lucca":"1","Napoli":"9","Avellino":"4","Lecce":"7","Trapani":"5","Caltanissetta":"1","Nuoro":"3","Milano":"2","Siracusa":"4","Modena":"3","Bari":"2","Messina":"2","Trieste":"1","L'Aquila":"1","Agrigento":"6","Alessandria":"3","Vercelli":"1","Frosinone":"1","Taranto":"7","Viterbo":"1","Palermo":"9"}},"2013":{"I":{"Italia":"180"},"Z":{"Nord-est":"25","Sud":"77","Nord-ovest":"18","Centro":"27","Isole":"33"},"R":{"Emilia-Romagna":"10","Marche":"3","Campania":"31","Lazio":"12","Friuli-Venezia Giulia":"4","Lombardia":"9","Veneto":"11","Sicilia":"27","Puglia":"23","Liguria":"1","Abruzzo":"1","Calabria":"17","Sardegna":"6","Umbria":"3","Basilicata":"3","Toscana":"9","Piemonte":"8","Molise":"2"},"P":{"Treviso":"2","Bologna":"3","Foggia":"1","Como":"1","Piacenza":"1","Benevento":"2","Salerno":"9","Brindisi":"9","Catanzaro":"5","Vibo Valentia":"3","Reggio di Calabria":"7","Firenze":"2","Siena":"2","Perugia":"2","Ascoli Piceno":"1","Potenza":"2","Matera":"1","Genova":"1","Bergamo":"4","Pordenone":"1","Udine":"2","Ravenna":"1","Pisa":"2","Grosseto":"2","Roma":"8","Cosenza":"2","Catania":"3","Torino":"2","Cuneo":"2","Mantova":"1","Vicenza":"3","Reggio nell'Emilia":"1","Rimini":"1","Terni":"1","Pesaro e Urbino":"1","Ancona":"1","Latina":"3","Isernia":"2","Caserta":"9","Cagliari":"2","Brescia":"1","Padova":"6","Lucca":"1","Napoli":"7","Avellino":"4","Lecce":"6","Trapani":"4","Caltanissetta":"1","Nuoro":"3","Milano":"2","Siracusa":"3","Modena":"3","Bari":"1","Messina":"2","Trieste":"1","L'Aquila":"1","Agrigento":"6","Alessandria":"3","Vercelli":"1","Frosinone":"1","Taranto":"6","Palermo":"8","Olbia-Tempio":"1"}},"2014":{"I":{"Italia":"172"},"Z":{"Nord-est":"25","Sud":"74","Nord-ovest":"21","Centro":"24","Isole":"28"},"R":{"Emilia-Romagna":"9","Marche":"2","Campania":"28","Lazio":"12","Friuli-Venezia Giulia":"4","Lombardia":"12","Veneto":"12","Sicilia":"24","Puglia":"23","Liguria":"1","Abruzzo":"1","Calabria":"17","Sardegna":"4","Umbria":"2","Basilicata":"3","Toscana":"8","Piemonte":"8","Molise":"2"},"P":{"Treviso":"2","Bologna":"2","Foggia":"1","Piacenza":"1","Benevento":"2","Salerno":"9","Brindisi":"9","Catanzaro":"5","Vibo Valentia":"2","Reggio di Calabria":"8","Firenze":"2","Siena":"2","Perugia":"2","Ascoli Piceno":"1","Potenza":"2","Matera":"1","Genova":"1","Bergamo":"4","Pordenone":"1","Udine":"2","Ravenna":"1","Pisa":"1","Grosseto":"2","Roma":"8","Cosenza":"2","Catania":"2","Torino":"2","Cuneo":"2","Mantova":"1","Vicenza":"3","Reggio nell'Emilia":"1","Rimini":"1","Pesaro e Urbino":"1","Latina":"3","Isernia":"2","Caserta":"8","Cagliari":"3","Brescia":"2","Padova":"5","Lucca":"1","Napoli":"6","Avellino":"3","Lecce":"6","Trapani":"3","Caltanissetta":"1","Milano":"5","Siracusa":"4","Modena":"3","Bari":"1","Messina":"2","Trieste":"1","L'Aquila":"1","Agrigento":"4","Alessandria":"3","Vercelli":"1","Frosinone":"1","Taranto":"6","Palermo":"8","Verona":"1","Belluno":"1","Olbia-Tempio":"1"}},"2015":{"I":{"Italia":"158"},"Z":{"Nord-est":"24","Sud":"66","Nord-ovest":"19","Centro":"23","Isole":"26"},"R":{"Emilia-Romagna":"9","Marche":"3","Campania":"21","Lazio":"13","Friuli-Venezia Giulia":"4","Lombardia":"11","Veneto":"11","Sicilia":"22","Puglia":"22","Liguria":"1","Abruzzo":"1","Calabria":"17","Sardegna":"4","Umbria":"2","Basilicata":"3","Toscana":"5","Piemonte":"7","Molise":"2"},"P":{"Treviso":"2","Bologna":"3","Foggia":"1","Piacenza":"1","Benevento":"2","Salerno":"6","Brindisi":"8","Catanzaro":"6","Vibo Valentia":"3","Reggio di Calabria":"7","Firenze":"1","Siena":"2","Perugia":"2","Ascoli Piceno":"1","Potenza":"2","Matera":"1","Genova":"1","Bergamo":"4","Pordenone":"1","Udine":"2","Ravenna":"1","Grosseto":"1","Roma":"9","Cosenza":"1","Catania":"2","Torino":"2","Cuneo":"2","Mantova":"1","Vicenza":"3","Reggio nell'Emilia":"1","Rimini":"1","Pesaro e Urbino":"1","Ancona":"1","Latina":"3","Isernia":"2","Caserta":"5","Cagliari":"2","Brescia":"2","Padova":"5","Lucca":"1","Napoli":"6","Avellino":"2","Lecce":"6","Trapani":"2","Caltanissetta":"1","Nuoro":"1","Milano":"4","Siracusa":"3","Modena":"2","Bari":"1","Messina":"2","Trieste":"1","L'Aquila":"1","Agrigento":"3","Alessandria":"2","Vercelli":"1","Frosinone":"1","Taranto":"6","Palermo":"9","Verona":"1","Sud Sardegna":"1"}},"2016":{"I":{"Italia":"156"},"Z":{"Nord-est":"22","Sud":"65","Nord-ovest":"21","Centro":"23","Isole":"25"},"R":{"Emilia-Romagna":"9","Marche":"3","Campania":"21","Lazio":"13","Friuli-Venezia Giulia":"4","Lombardia":"13","Veneto":"9","Sicilia":"21","Puglia":"23","Liguria":"1","Abruzzo":"1","Calabria":"16","Sardegna":"4","Umbria":"2","Basilicata":"3","Toscana":"5","Piemonte":"7","Molise":"1"},"P":{"Treviso":"2","Bologna":"3","Foggia":"3","Como":"1","Piacenza":"1","Benevento":"2","Salerno":"6","Brindisi":"8","Catanzaro":"7","Vibo Valentia":"1","Reggio di Calabria":"7","Firenze":"1","Siena":"2","Perugia":"2","Ascoli Piceno":"1","Potenza":"2","Matera":"1","Genova":"1","Bergamo":"4","Pordenone":"1","Udine":"2","Grosseto":"1","Roma":"10","Cosenza":"1","Catania":"2","Torino":"2","Cuneo":"2","Mantova":"1","Vicenza":"2","Reggio nell'Emilia":"1","Rimini":"2","Pesaro e Urbino":"1","Ancona":"1","Latina":"2","Isernia":"1","Caserta":"5","Cagliari":"2","Brescia":"2","Padova":"4","Lucca":"1","Napoli":"5","Avellino":"3","Lecce":"6","Trapani":"1","Caltanissetta":"1","Nuoro":"1","Milano":"5","Siracusa":"3","Modena":"2","Messina":"2","Trieste":"1","L'Aquila":"1","Agrigento":"3","Alessandria":"2","Vercelli":"1","Frosinone":"1","Taranto":"6","Palermo":"9","Verona":"1","Sud Sardegna":"1"}},"2017":{"I":{"Italia":"150"},"Z":{"Nord-est":"22","Sud":"61","Nord-ovest":"22","Centro":"19","Isole":"26"},"R":{"Emilia-Romagna":"7","Marche":"1","Campania":"21","Lazio":"11","Friuli-Venezia Giulia":"4","Lombardia":"15","Veneto":"10","Sicilia":"22","Puglia":"22","Liguria":"1","Abruzzo":"1","Calabria":"14","Sardegna":"4","Umbria":"2","Basilicata":"2","Toscana":"5","Piemonte":"6","Molise":"1","Trentino Alto Adige \/ S\u00fcdtirol":"1","Provincia Autonoma Bolzano \/ Bozen":"1"},"P":{"Treviso":"1","Bologna":"3","Foggia":"3","Como":"1","Piacenza":"1","Benevento":"3","Salerno":"4","Brindisi":"8","Catanzaro":"6","Reggio di Calabria":"6","Firenze":"1","Siena":"2","Perugia":"2","Ascoli Piceno":"1","Potenza":"2","Genova":"1","Bergamo":"5","Pordenone":"1","Udine":"2","Grosseto":"1","Roma":"7","Cosenza":"2","Catania":"2","Torino":"2","Cuneo":"1","Mantova":"1","Vicenza":"4","Reggio nell'Emilia":"1","Rimini":"1","Latina":"3","Isernia":"1","Caserta":"6","Cagliari":"2","Brescia":"2","Padova":"5","Lucca":"1","Napoli":"5","Avellino":"3","Lecce":"6","Trapani":"3","Caltanissetta":"1","Milano":"5","Siracusa":"3","Modena":"1","Messina":"2","Trieste":"1","L'Aquila":"1","Agrigento":"2","Alessandria":"2","Vercelli":"1","Frosinone":"1","Taranto":"5","Palermo":"9","Sud Sardegna":"1","Lecco":"1","Bolzano \/ Bozen":"1","Sassari":"1"}},"2018":{"I":{"Italia":"145"},"Z":{"Nord-est":"22","Sud":"56","Nord-ovest":"24","Centro":"20","Isole":"23"},"R":{"Emilia-Romagna":"9","Marche":"1","Campania":"18","Lazio":"10","Friuli-Venezia Giulia":"4","Lombardia":"17","Veneto":"8","Sicilia":"19","Puglia":"21","Liguria":"1","Calabria":"14","Sardegna":"4","Umbria":"3","Basilicata":"2","Toscana":"6","Piemonte":"6","Molise":"1","Trentino Alto Adige \/ S\u00fcdtirol":"1","Provincia Autonoma Bolzano \/ Bozen":"1"},"P":{"Treviso":"1","Bologna":"3","Foggia":"3","Como":"1","Piacenza":"1","Benevento":"3","Salerno":"4","Brindisi":"8","Catanzaro":"7","Vibo Valentia":"2","Reggio di Calabria":"5","Firenze":"1","Siena":"2","Perugia":"3","Ascoli Piceno":"1","Potenza":"2","Genova":"1","Bergamo":"7","Pordenone":"1","Udine":"2","Ravenna":"1","Grosseto":"2","Roma":"6","Catania":"2","Torino":"2","Cuneo":"1","Mantova":"1","Vicenza":"4","Reggio nell'Emilia":"1","Rimini":"1","Latina":"3","Isernia":"1","Caserta":"5","Cagliari":"2","Brescia":"2","Padova":"3","Lucca":"1","Napoli":"5","Avellino":"1","Lecce":"5","Caltanissetta":"1","Milano":"6","Siracusa":"3","Modena":"2","Messina":"2","Trieste":"1","Agrigento":"2","Alessandria":"2","Vercelli":"1","Frosinone":"1","Taranto":"5","Palermo":"9","Sud Sardegna":"1","Bolzano \/ Bozen":"1","Oristano":"1"}},"2019":{"I":{"Italia":"114"},"Z":{"Nord-est":"22","Sud":"33","Nord-ovest":"24","Centro":"18","Isole":"17"},"R":{"Emilia-Romagna":"7","Marche":"1","Campania":"12","Lazio":"7","Friuli-Venezia Giulia":"5","Lombardia":"14","Veneto":"8","Sicilia":"15","Puglia":"12","Liguria":"1","Calabria":"6","Sardegna":"2","Umbria":"5","Basilicata":"2","Toscana":"5","Piemonte":"9","Molise":"1","Trentino Alto Adige \/ S\u00fcdtirol":"2","Provincia Autonoma Bolzano \/ Bozen":"1","Provincia Autonoma Trento":"1"},"P":{"Treviso":"1","Bologna":"2","Foggia":"3","Como":"2","Piacenza":"1","Benevento":"1","Salerno":"2","Brindisi":"5","Catanzaro":"4","Reggio di Calabria":"2","Firenze":"1","Siena":"1","Perugia":"5","Ascoli Piceno":"1","Potenza":"2","Genova":"1","Bergamo":"6","Pordenone":"1","Udine":"2","Ravenna":"1","Grosseto":"2","Roma":"4","Catania":"2","Torino":"2","Cuneo":"1","Mantova":"1","Vicenza":"4","Reggio nell'Emilia":"1","Rimini":"1","Latina":"2","Isernia":"1","Caserta":"4","Cagliari":"2","Brescia":"2","Padova":"3","Lucca":"1","Napoli":"3","Avellino":"2","Lecce":"3","Caltanissetta":"1","Milano":"3","Siracusa":"2","Modena":"1","Trieste":"2","Agrigento":"1","Alessandria":"5","Vercelli":"1","Frosinone":"1","Taranto":"1","Palermo":"9","Bolzano \/ Bozen":"1","Trento":"1"}},"2020":{"I":{"Italia":"126"},"Z":{"Nord-est":"22","Sud":"42","Nord-ovest":"22","Centro":"23","Isole":"17"},"R":{"Emilia-Romagna":"8","Campania":"13","Lazio":"13","Friuli-Venezia Giulia":"3","Lombardia":"13","Veneto":"9","Sicilia":"15","Puglia":"18","Liguria":"1","Calabria":"8","Sardegna":"2","Umbria":"5","Basilicata":"2","Toscana":"5","Piemonte":"8","Molise":"1","Trentino Alto Adige \/ S\u00fcdtirol":"2","Provincia Autonoma Bolzano \/ Bozen":"1","Provincia Autonoma Trento":"1"},"P":{"Treviso":"2","Bologna":"2","Foggia":"2","Como":"2","Piacenza":"1","Benevento":"1","Salerno":"3","Brindisi":"8","Catanzaro":"5","Reggio di Calabria":"3","Siena":"2","Perugia":"5","Potenza":"2","Genova":"1","Bergamo":"5","Pordenone":"1","Udine":"1","Ravenna":"1","Grosseto":"2","Roma":"10","Catania":"3","Torino":"2","Cuneo":"1","Mantova":"1","Vicenza":"4","Reggio nell'Emilia":"2","Rimini":"1","Latina":"2","Isernia":"1","Caserta":"5","Cagliari":"2","Brescia":"2","Padova":"3","Lucca":"1","Napoli":"3","Avellino":"1","Lecce":"4","Caltanissetta":"1","Milano":"2","Siracusa":"3","Modena":"1","Trieste":"1","Alessandria":"4","Vercelli":"1","Frosinone":"1","Taranto":"4","Palermo":"8","Lecco":"1","Bolzano \/ Bozen":"1","Trento":"1"}}}