{"2012":{"I":{"Italia":"2186"},"Z":{"Nord-est":"674","Sud":"136","Nord-ovest":"962","Centro":"383","Isole":"31"},"R":{"Friuli-Venezia Giulia":"44","Veneto":"285","Lazio":"116","Molise":"3","Calabria":"6","Emilia-Romagna":"321","Puglia":"25","Marche":"106","Sardegna":"2","Piemonte":"255","Liguria":"28","Trentino Alto Adige \/ S\u00fcdtirol":"24","Abruzzo":"29","Sicilia":"29","Umbria":"27","Toscana":"134","Basilicata":"5","Campania":"68","Valle d'Aosta \/ Vall\u00e9e d'Aoste":"1","Lombardia":"678","Provincia Autonoma Bolzano \/ Bozen":"5","Provincia Autonoma Trento":"19"},"P":{"Rovigo":"8","Gorizia":"4","Trieste":"3","Frosinone":"14","Taranto":"2","Savona":"4","Brescia":"78","Vicenza":"91","Modena":"69","Forl\u00ec-Cesena":"16","Arezzo":"29","Siena":"7","Grosseto":"1","Perugia":"22","Latina":"10","Campobasso":"2","Lecce":"6","Potenza":"4","Enna":"2","Monza e della Brianza":"79","Torino":"162","Imperia":"1","Genova":"16","Varese":"92","Mantova":"18","Udine":"16","Piacenza":"9","Massa-Carrara":"9","Lucca":"14","Pistoia":"5","Prato":"10","Pisa":"8","Pesaro e Urbino":"24","Macerata":"23","Teramo":"9","Benevento":"4","Salerno":"12","Foggia":"2","Bari":"12","Cosenza":"4","Trapani":"4","Sassari":"1","Carbonia-Iglesias":"1","Alessandria":"18","La Spezia":"7","Lecco":"39","Milano":"227","Bergamo":"73","Pavia":"18","Trento":"19","Bologna":"89","Ferrara":"15","Firenze":"49","Ascoli Piceno":"14","Rieti":"13","Roma":"74","L'Aquila":"7","Pescara":"9","Reggio di Calabria":"1","Catania":"16","Siracusa":"2","Fermo":"3","Vercelli":"5","Biella":"5","Verbano-Cusio-Ossola":"5","Novara":"18","Como":"24","Sondrio":"8","Cremona":"13","Bolzano \/ Bozen":"5","Verona":"31","Belluno":"18","Treviso":"50","Venezia":"14","Padova":"73","Reggio nell'Emilia":"51","Ravenna":"25","Napoli":"37","Avellino":"1","Brindisi":"1","Palermo":"1","Messina":"1","Parma":"21","Rimini":"26","Livorno":"2","Ancona":"42","Isernia":"1","Matera":"1","Catanzaro":"1","Cuneo":"37","Terni":"5","Valle d'Aosta \/ Vall\u00e9e d'Aoste":"1","Lodi":"9","Viterbo":"5","Chieti":"4","Agrigento":"3","Caserta":"14","Asti":"5","Barletta-Andria-Trani":"2","Pordenone":"21"}},"2013":{"I":{"Italia":"2067"},"Z":{"Nord-est":"647","Sud":"129","Nord-ovest":"915","Centro":"350","Isole":"26"},"R":{"Friuli-Venezia Giulia":"42","Veneto":"279","Lazio":"101","Molise":"2","Calabria":"6","Emilia-Romagna":"298","Puglia":"21","Marche":"104","Sardegna":"1","Piemonte":"239","Liguria":"28","Trentino Alto Adige \/ S\u00fcdtirol":"28","Abruzzo":"33","Sicilia":"25","Umbria":"21","Toscana":"124","Basilicata":"7","Campania":"60","Valle d'Aosta \/ Vall\u00e9e d'Aoste":"1","Lombardia":"647","Provincia Autonoma Bolzano \/ Bozen":"9","Provincia Autonoma Trento":"19"},"P":{"Rovigo":"8","Gorizia":"5","Trieste":"2","Frosinone":"14","Savona":"3","Brescia":"74","Vicenza":"89","Modena":"64","Forl\u00ec-Cesena":"16","Arezzo":"30","Siena":"5","Grosseto":"1","Perugia":"17","Latina":"13","Campobasso":"1","Lecce":"4","Potenza":"6","Enna":"2","Monza e della Brianza":"81","Torino":"155","Imperia":"1","Genova":"16","Varese":"88","Mantova":"17","Udine":"14","Piacenza":"7","Massa-Carrara":"7","Lucca":"11","Pistoia":"3","Prato":"12","Pisa":"9","Pesaro e Urbino":"24","Macerata":"24","Teramo":"11","Benevento":"4","Salerno":"8","Foggia":"2","Bari":"11","Cosenza":"4","Trapani":"3","Carbonia-Iglesias":"1","Alessandria":"12","La Spezia":"8","Lecco":"38","Milano":"200","Bergamo":"79","Pavia":"18","Trento":"19","Bologna":"81","Ferrara":"15","Firenze":"44","Ascoli Piceno":"11","Rieti":"10","Roma":"59","L'Aquila":"9","Pescara":"9","Reggio di Calabria":"1","Catania":"14","Siracusa":"2","Fermo":"4","Vercelli":"4","Biella":"7","Verbano-Cusio-Ossola":"7","Novara":"14","Como":"22","Sondrio":"6","Cremona":"15","Bolzano \/ Bozen":"9","Verona":"31","Belluno":"15","Treviso":"49","Venezia":"12","Padova":"75","Reggio nell'Emilia":"50","Ravenna":"22","Napoli":"34","Avellino":"2","Brindisi":"1","Palermo":"1","Parma":"17","Rimini":"26","Livorno":"2","Ancona":"41","Isernia":"1","Matera":"1","Catanzaro":"1","Cuneo":"34","Terni":"4","Valle d'Aosta \/ Vall\u00e9e d'Aoste":"1","Lodi":"9","Viterbo":"5","Chieti":"4","Agrigento":"3","Caserta":"12","Asti":"6","Barletta-Andria-Trani":"3","Pordenone":"21"}},"2014":{"I":{"Italia":"2046"},"Z":{"Nord-est":"641","Sud":"130","Nord-ovest":"905","Centro":"345","Isole":"25"},"R":{"Friuli-Venezia Giulia":"45","Veneto":"270","Lazio":"98","Molise":"4","Calabria":"8","Emilia-Romagna":"299","Puglia":"22","Marche":"106","Sardegna":"2","Piemonte":"226","Liguria":"30","Trentino Alto Adige \/ S\u00fcdtirol":"27","Abruzzo":"34","Sicilia":"23","Umbria":"25","Toscana":"116","Basilicata":"7","Campania":"55","Valle d'Aosta \/ Vall\u00e9e d'Aoste":"1","Lombardia":"648","Provincia Autonoma Bolzano \/ Bozen":"10","Provincia Autonoma Trento":"17"},"P":{"Rovigo":"8","Gorizia":"4","Trieste":"2","Frosinone":"12","Savona":"3","Brescia":"78","Vicenza":"85","Modena":"67","Forl\u00ec-Cesena":"16","Arezzo":"30","Siena":"7","Grosseto":"1","Perugia":"19","Latina":"13","Campobasso":"2","Lecce":"6","Potenza":"6","Enna":"2","Monza e della Brianza":"82","Torino":"149","Imperia":"1","Genova":"16","Varese":"84","Mantova":"17","Udine":"18","Piacenza":"8","Massa-Carrara":"7","Lucca":"8","Pistoia":"4","Prato":"11","Pisa":"7","Pesaro e Urbino":"25","Macerata":"24","Teramo":"10","Benevento":"4","Salerno":"8","Foggia":"2","Bari":"11","Cosenza":"6","Trapani":"2","Carbonia-Iglesias":"1","Alessandria":"12","La Spezia":"10","Lecco":"40","Milano":"191","Bergamo":"77","Pavia":"20","Trento":"17","Bologna":"81","Ferrara":"18","Firenze":"39","Ascoli Piceno":"11","Rieti":"11","Roma":"56","L'Aquila":"13","Pescara":"7","Reggio di Calabria":"1","Catania":"15","Siracusa":"3","Fermo":"4","Vercelli":"4","Biella":"7","Verbano-Cusio-Ossola":"8","Novara":"14","Como":"26","Sondrio":"7","Cremona":"17","Bolzano \/ Bozen":"10","Verona":"33","Belluno":"15","Treviso":"48","Venezia":"14","Padova":"67","Reggio nell'Emilia":"46","Ravenna":"21","Napoli":"28","Avellino":"1","Brindisi":"1","Palermo":"1","Parma":"17","Rimini":"25","Livorno":"2","Ancona":"42","Isernia":"2","Matera":"1","Catanzaro":"1","Cuneo":"27","Terni":"6","Valle d'Aosta \/ Vall\u00e9e d'Aoste":"1","Lodi":"9","Viterbo":"6","Chieti":"4","Caserta":"14","Asti":"5","Barletta-Andria-Trani":"2","Pordenone":"21","Cagliari":"1"}},"2015":{"I":{"Italia":"1977"},"Z":{"Nord-est":"626","Sud":"124","Nord-ovest":"859","Centro":"340","Isole":"28"},"R":{"Friuli-Venezia Giulia":"40","Veneto":"268","Lazio":"95","Molise":"5","Calabria":"6","Emilia-Romagna":"291","Puglia":"30","Marche":"105","Sardegna":"5","Piemonte":"215","Liguria":"35","Trentino Alto Adige \/ S\u00fcdtirol":"27","Abruzzo":"31","Sicilia":"23","Umbria":"24","Toscana":"116","Basilicata":"8","Campania":"44","Lombardia":"609","Provincia Autonoma Bolzano \/ Bozen":"8","Provincia Autonoma Trento":"19"},"P":{"Rovigo":"9","Gorizia":"4","Trieste":"1","Frosinone":"11","Taranto":"1","Savona":"4","Brescia":"72","Vicenza":"87","Modena":"64","Forl\u00ec-Cesena":"16","Arezzo":"29","Siena":"9","Grosseto":"1","Perugia":"22","Latina":"12","Campobasso":"3","Lecce":"8","Potenza":"7","Enna":"2","Monza e della Brianza":"77","Torino":"136","Genova":"19","Varese":"82","Mantova":"17","Udine":"15","Piacenza":"7","Massa-Carrara":"7","Lucca":"11","Pistoia":"3","Prato":"10","Pisa":"6","Pesaro e Urbino":"19","Macerata":"22","Teramo":"10","Benevento":"2","Salerno":"5","Foggia":"2","Bari":"15","Cosenza":"5","Trapani":"3","Sassari":"1","Alessandria":"12","La Spezia":"12","Lecco":"41","Milano":"173","Bergamo":"76","Pavia":"17","Trento":"19","Bologna":"86","Ferrara":"15","Firenze":"39","Ascoli Piceno":"9","Rieti":"10","Roma":"57","L'Aquila":"9","Pescara":"8","Reggio di Calabria":"1","Catania":"16","Siracusa":"1","Fermo":"7","Vercelli":"3","Biella":"5","Verbano-Cusio-Ossola":"8","Novara":"14","Como":"26","Sondrio":"6","Cremona":"15","Bolzano \/ Bozen":"8","Verona":"30","Belluno":"16","Treviso":"45","Venezia":"18","Padova":"63","Reggio nell'Emilia":"43","Ravenna":"18","Napoli":"22","Avellino":"2","Brindisi":"1","Parma":"17","Rimini":"25","Livorno":"1","Ancona":"48","Isernia":"2","Matera":"1","Cuneo":"31","Terni":"2","Lodi":"7","Viterbo":"5","Chieti":"4","Caserta":"13","Asti":"6","Barletta-Andria-Trani":"3","Pordenone":"20","Cagliari":"2","Ragusa":"1","Sud Sardegna":"1","Oristano":"1"}},"2016":{"I":{"Italia":"1952"},"Z":{"Nord-est":"624","Sud":"116","Nord-ovest":"835","Centro":"347","Isole":"30"},"R":{"Friuli-Venezia Giulia":"42","Veneto":"259","Lazio":"98","Molise":"5","Calabria":"7","Emilia-Romagna":"298","Puglia":"34","Marche":"101","Sardegna":"7","Piemonte":"214","Liguria":"34","Trentino Alto Adige \/ S\u00fcdtirol":"25","Abruzzo":"21","Sicilia":"23","Umbria":"28","Toscana":"120","Basilicata":"8","Campania":"41","Lombardia":"587","Provincia Autonoma Bolzano \/ Bozen":"7","Provincia Autonoma Trento":"18"},"P":{"Rovigo":"8","Gorizia":"2","Trieste":"2","Frosinone":"8","Taranto":"1","Savona":"3","Brescia":"74","Vicenza":"81","Modena":"66","Forl\u00ec-Cesena":"16","Arezzo":"28","Siena":"10","Grosseto":"1","Perugia":"24","Latina":"16","Campobasso":"3","Lecce":"12","Potenza":"7","Enna":"3","Monza e della Brianza":"69","Torino":"137","Genova":"21","Varese":"80","Mantova":"17","Udine":"13","Piacenza":"7","Massa-Carrara":"7","Lucca":"10","Pistoia":"5","Prato":"9","Pisa":"6","Pesaro e Urbino":"20","Macerata":"20","Teramo":"6","Benevento":"1","Salerno":"3","Foggia":"2","Bari":"15","Cosenza":"6","Trapani":"3","Sassari":"2","Alessandria":"14","La Spezia":"10","Lecco":"35","Milano":"171","Bergamo":"71","Pavia":"17","Trento":"18","Bologna":"87","Ferrara":"18","Firenze":"43","Ascoli Piceno":"11","Rieti":"9","Roma":"59","L'Aquila":"7","Pescara":"5","Reggio di Calabria":"1","Catania":"15","Siracusa":"1","Fermo":"7","Vercelli":"3","Biella":"6","Verbano-Cusio-Ossola":"8","Novara":"14","Como":"26","Sondrio":"6","Cremona":"15","Bolzano \/ Bozen":"7","Verona":"31","Belluno":"13","Treviso":"44","Venezia":"19","Padova":"63","Reggio nell'Emilia":"45","Ravenna":"17","Napoli":"22","Brindisi":"2","Parma":"16","Rimini":"26","Livorno":"1","Ancona":"43","Isernia":"2","Matera":"1","Cuneo":"28","Terni":"4","Lodi":"6","Viterbo":"6","Chieti":"3","Caserta":"15","Asti":"4","Barletta-Andria-Trani":"2","Pordenone":"25","Cagliari":"3","Ragusa":"1","Sud Sardegna":"1","Oristano":"1"}},"2017":{"I":{"Italia":"1960"},"Z":{"Nord-est":"625","Sud":"115","Nord-ovest":"845","Centro":"344","Isole":"31"},"R":{"Friuli-Venezia Giulia":"40","Veneto":"254","Lazio":"88","Molise":"5","Calabria":"6","Emilia-Romagna":"305","Puglia":"30","Marche":"98","Sardegna":"7","Piemonte":"204","Liguria":"35","Trentino Alto Adige \/ S\u00fcdtirol":"26","Abruzzo":"25","Sicilia":"24","Umbria":"30","Toscana":"128","Basilicata":"6","Campania":"43","Lombardia":"606","Provincia Autonoma Bolzano \/ Bozen":"6","Provincia Autonoma Trento":"20"},"P":{"Rovigo":"8","Gorizia":"2","Trieste":"2","Frosinone":"8","Taranto":"1","Savona":"3","Brescia":"73","Vicenza":"81","Modena":"64","Forl\u00ec-Cesena":"16","Arezzo":"32","Siena":"8","Grosseto":"2","Perugia":"25","Latina":"14","Campobasso":"3","Lecce":"8","Potenza":"5","Enna":"3","Monza e della Brianza":"73","Torino":"129","Genova":"21","Varese":"80","Mantova":"17","Udine":"14","Piacenza":"8","Massa-Carrara":"7","Lucca":"9","Pistoia":"5","Prato":"11","Pisa":"5","Pesaro e Urbino":"22","Macerata":"20","Teramo":"8","Benevento":"1","Salerno":"4","Foggia":"1","Bari":"17","Cosenza":"5","Trapani":"3","Sassari":"2","Alessandria":"14","La Spezia":"11","Lecco":"34","Milano":"185","Bergamo":"73","Pavia":"19","Trento":"20","Bologna":"91","Ferrara":"18","Firenze":"48","Ascoli Piceno":"8","Rieti":"7","Roma":"55","L'Aquila":"8","Pescara":"6","Reggio di Calabria":"1","Catania":"14","Siracusa":"3","Fermo":"7","Vercelli":"2","Biella":"5","Verbano-Cusio-Ossola":"8","Novara":"11","Como":"26","Sondrio":"6","Cremona":"14","Bolzano \/ Bozen":"6","Verona":"31","Belluno":"12","Treviso":"44","Venezia":"17","Padova":"61","Reggio nell'Emilia":"51","Ravenna":"14","Napoli":"22","Brindisi":"1","Parma":"19","Rimini":"24","Livorno":"1","Ancona":"41","Isernia":"2","Matera":"1","Cuneo":"30","Terni":"5","Lodi":"6","Viterbo":"4","Chieti":"3","Caserta":"16","Asti":"5","Barletta-Andria-Trani":"2","Pordenone":"22","Cagliari":"3","Ragusa":"1","Sud Sardegna":"1","Oristano":"1"}},"2018":{"I":{"Italia":"1939"},"Z":{"Nord-est":"646","Sud":"102","Nord-ovest":"817","Centro":"342","Isole":"32"},"R":{"Friuli-Venezia Giulia":"45","Veneto":"260","Lazio":"92","Molise":"5","Calabria":"6","Emilia-Romagna":"317","Puglia":"27","Marche":"103","Sardegna":"6","Piemonte":"212","Liguria":"34","Trentino Alto Adige \/ S\u00fcdtirol":"24","Abruzzo":"19","Sicilia":"26","Umbria":"28","Toscana":"119","Basilicata":"6","Campania":"39","Lombardia":"571","Provincia Autonoma Bolzano \/ Bozen":"7","Provincia Autonoma Trento":"17"},"P":{"Rovigo":"8","Gorizia":"2","Trieste":"2","Frosinone":"10","Taranto":"2","Savona":"2","Brescia":"69","Vicenza":"77","Modena":"71","Forl\u00ec-Cesena":"15","Arezzo":"30","Siena":"5","Grosseto":"1","Perugia":"25","Latina":"14","Campobasso":"4","Lecce":"7","Potenza":"5","Enna":"3","Monza e della Brianza":"78","Torino":"138","Genova":"24","Varese":"72","Mantova":"16","Udine":"17","Piacenza":"7","Massa-Carrara":"5","Lucca":"10","Pistoia":"7","Prato":"9","Pisa":"5","Pesaro e Urbino":"22","Macerata":"19","Teramo":"7","Benevento":"1","Salerno":"3","Foggia":"1","Bari":"14","Cosenza":"4","Trapani":"3","Sassari":"2","Alessandria":"14","La Spezia":"8","Lecco":"33","Milano":"168","Bergamo":"69","Pavia":"15","Trento":"17","Bologna":"90","Ferrara":"19","Firenze":"45","Ascoli Piceno":"8","Rieti":"7","Roma":"58","L'Aquila":"7","Pescara":"4","Reggio di Calabria":"1","Catania":"16","Siracusa":"2","Fermo":"7","Vercelli":"2","Biella":"4","Verbano-Cusio-Ossola":"8","Novara":"14","Como":"27","Sondrio":"5","Cremona":"16","Bolzano \/ Bozen":"7","Verona":"35","Belluno":"14","Treviso":"42","Venezia":"15","Padova":"69","Reggio nell'Emilia":"61","Ravenna":"15","Napoli":"22","Brindisi":"1","Parma":"15","Rimini":"24","Livorno":"2","Ancona":"47","Isernia":"1","Matera":"1","Catanzaro":"1","Cuneo":"28","Terni":"3","Lodi":"3","Viterbo":"3","Chieti":"1","Agrigento":"1","Caserta":"13","Asti":"4","Barletta-Andria-Trani":"2","Pordenone":"24","Cagliari":"2","Ragusa":"1","Sud Sardegna":"2"}},"2019":{"I":{"Italia":"1936"},"Z":{"Nord-est":"629","Sud":"97","Nord-ovest":"830","Centro":"345","Isole":"35"},"R":{"Friuli-Venezia Giulia":"44","Veneto":"245","Lazio":"98","Molise":"4","Calabria":"7","Emilia-Romagna":"317","Puglia":"25","Marche":"103","Sardegna":"6","Piemonte":"215","Liguria":"38","Trentino Alto Adige \/ S\u00fcdtirol":"23","Abruzzo":"22","Sicilia":"29","Umbria":"29","Toscana":"115","Basilicata":"5","Campania":"34","Lombardia":"577","Provincia Autonoma Bolzano \/ Bozen":"7","Provincia Autonoma Trento":"16"},"P":{"Rovigo":"6","Gorizia":"2","Trieste":"3","Frosinone":"8","Taranto":"2","Savona":"4","Brescia":"65","Vicenza":"76","Modena":"72","Forl\u00ec-Cesena":"17","Arezzo":"28","Siena":"5","Grosseto":"1","Perugia":"26","Latina":"11","Campobasso":"3","Lecce":"7","Potenza":"5","Enna":"3","Monza e della Brianza":"72","Torino":"147","Genova":"26","Varese":"73","Mantova":"18","Udine":"16","Piacenza":"9","Massa-Carrara":"7","Lucca":"13","Pistoia":"4","Prato":"13","Pisa":"7","Pesaro e Urbino":"21","Macerata":"21","Teramo":"8","Benevento":"2","Salerno":"2","Foggia":"1","Bari":"13","Cosenza":"3","Trapani":"3","Sassari":"1","Alessandria":"14","La Spezia":"8","Lecco":"37","Milano":"177","Bergamo":"66","Pavia":"20","Trento":"16","Bologna":"83","Ferrara":"21","Firenze":"35","Ascoli Piceno":"9","Rieti":"9","Roma":"67","L'Aquila":"8","Pescara":"4","Reggio di Calabria":"2","Catania":"15","Siracusa":"2","Fermo":"8","Vercelli":"2","Biella":"3","Verbano-Cusio-Ossola":"7","Novara":"11","Como":"24","Sondrio":"6","Cremona":"16","Bolzano \/ Bozen":"7","Verona":"30","Belluno":"9","Treviso":"39","Venezia":"22","Padova":"63","Reggio nell'Emilia":"60","Ravenna":"16","Napoli":"21","Avellino":"1","Palermo":"2","Messina":"1","Parma":"13","Rimini":"26","Livorno":"2","Ancona":"44","Isernia":"1","Catanzaro":"1","Cuneo":"27","Terni":"3","Lodi":"3","Viterbo":"3","Chieti":"2","Agrigento":"2","Caserta":"8","Asti":"4","Barletta-Andria-Trani":"2","Pordenone":"23","Cagliari":"3","Ragusa":"1","Sud Sardegna":"2","Crotone":"1"}},"2020":{"I":{"Italia":"1964"},"Z":{"Nord-est":"657","Sud":"115","Nord-ovest":"811","Centro":"344","Isole":"37"},"R":{"Friuli-Venezia Giulia":"45","Veneto":"283","Lazio":"95","Molise":"7","Calabria":"7","Emilia-Romagna":"305","Puglia":"26","Marche":"109","Sardegna":"8","Piemonte":"207","Liguria":"39","Trentino Alto Adige \/ S\u00fcdtirol":"24","Abruzzo":"25","Sicilia":"29","Umbria":"31","Toscana":"109","Basilicata":"7","Campania":"43","Valle d'Aosta \/ Vall\u00e9e d'Aoste":"1","Lombardia":"564","Provincia Autonoma Bolzano \/ Bozen":"8","Provincia Autonoma Trento":"16"},"P":{"Rovigo":"6","Gorizia":"2","Trieste":"5","Frosinone":"7","Taranto":"3","Savona":"5","Brescia":"67","Vicenza":"89","Modena":"67","Forl\u00ec-Cesena":"17","Arezzo":"28","Siena":"5","Grosseto":"1","Perugia":"28","Latina":"10","Campobasso":"6","Lecce":"6","Potenza":"7","Enna":"3","Monza e della Brianza":"67","Torino":"138","Genova":"27","Varese":"69","Mantova":"19","Udine":"16","Piacenza":"8","Massa-Carrara":"7","Lucca":"9","Pistoia":"5","Prato":"11","Pisa":"6","Pesaro e Urbino":"22","Macerata":"18","Teramo":"10","Benevento":"1","Salerno":"5","Foggia":"2","Bari":"12","Cosenza":"4","Trapani":"3","Alessandria":"14","La Spezia":"7","Lecco":"39","Milano":"179","Bergamo":"61","Pavia":"18","Trento":"16","Bologna":"79","Ferrara":"19","Firenze":"35","Ascoli Piceno":"9","Rieti":"9","Roma":"66","L'Aquila":"8","Pescara":"5","Reggio di Calabria":"2","Catania":"12","Siracusa":"1","Fermo":"9","Vercelli":"2","Biella":"4","Verbano-Cusio-Ossola":"6","Novara":"8","Como":"22","Sondrio":"5","Cremona":"14","Bolzano \/ Bozen":"8","Verona":"39","Belluno":"9","Treviso":"45","Venezia":"20","Padova":"75","Reggio nell'Emilia":"55","Ravenna":"17","Napoli":"24","Avellino":"3","Palermo":"4","Messina":"2","Parma":"16","Rimini":"27","Livorno":"2","Ancona":"51","Isernia":"1","Catanzaro":"1","Cuneo":"26","Terni":"3","Valle d'Aosta \/ Vall\u00e9e d'Aoste":"1","Lodi":"4","Viterbo":"3","Chieti":"2","Agrigento":"4","Caserta":"10","Asti":"9","Barletta-Andria-Trani":"3","Pordenone":"22","Cagliari":"6","Sud Sardegna":"2"}}}