{"2012":{"I":{"Italia":"303"},"Z":{"Nord-ovest":"113","Isole":"15","Nord-est":"56","Centro":"57","Sud":"62"}},"2013":{"I":{"Italia":"324"},"Z":{"Nord-ovest":"122","Isole":"16","Nord-est":"61","Centro":"60","Sud":"65"}},"2014":{"I":{"Italia":"336"},"Z":{"Nord-ovest":"124","Isole":"15","Nord-est":"57","Centro":"68","Sud":"72"}},"2015":{"I":{"Italia":"348"},"Z":{"Nord-ovest":"131","Isole":"15","Nord-est":"58","Centro":"72","Sud":"72"}},"2016":{"I":{"Italia":"340"},"Z":{"Nord-ovest":"129","Isole":"16","Nord-est":"56","Centro":"70","Sud":"69"}},"2017":{"I":{"Italia":"343"},"Z":{"Nord-ovest":"132","Isole":"18","Nord-est":"60","Centro":"65","Sud":"68"}},"2018":{"I":{"Italia":"346"},"Z":{"Nord-ovest":"136","Isole":"24","Nord-est":"61","Centro":"65","Sud":"60"}},"2019":{"I":{"Italia":"337"},"Z":{"Nord-ovest":"137","Isole":"16","Nord-est":"57","Centro":"67","Sud":"60"},"R":{"Piemonte":"21","Liguria":"4","Lombardia":"112","Trentino Alto Adige \/ S\u00fcdtirol":"6","Veneto":"22","Emilia-Romagna":"23","Friuli-Venezia Giulia":"6","Toscana":"12","Umbria":"5","Lazio":"31","Abruzzo":"11","Campania":"20","Puglia":"17","Sicilia":"13","Calabria":"3","Sardegna":"3","Marche":"19","Molise":"5","Basilicata":"4","Provincia Autonoma Bolzano \/ Bozen":"3","Provincia Autonoma Trento":"3"},"P":{"Torino":"11","Cuneo":"3","Asti":"3","Alessandria":"4","Savona":"2","La Spezia":"2","Varese":"3","Como":"2","Lecco":"2","Sondrio":"1","Milano":"81","Bergamo":"5","Brescia":"5","Pavia":"5","Lodi":"1","Cremona":"3","Bolzano \/ Bozen":"3","Trento":"3","Verona":"5","Vicenza":"5","Belluno":"1","Treviso":"3","Padova":"7","Rovigo":"1","Udine":"4","Trieste":"2","Piacenza":"3","Parma":"4","Reggio nell'Emilia":"2","Modena":"3","Bologna":"4","Ferrara":"4","Ravenna":"1","Forl\u00ec-Cesena":"1","Rimini":"1","Lucca":"1","Pistoia":"1","Firenze":"4","Prato":"1","Livorno":"3","Pisa":"1","Siena":"1","Perugia":"5","Pesaro e Urbino":"1","Ancona":"3","Macerata":"4","Ascoli Piceno":"6","Roma":"27","Latina":"1","Frosinone":"3","L'Aquila":"3","Teramo":"2","Pescara":"1","Chieti":"5","Isernia":"1","Campobasso":"4","Caserta":"5","Benevento":"2","Napoli":"8","Avellino":"1","Salerno":"4","Foggia":"5","Bari":"3","Taranto":"3","Brindisi":"1","Lecce":"3","Potenza":"2","Matera":"2","Cosenza":"3","Palermo":"3","Messina":"3","Agrigento":"1","Catania":"3","Siracusa":"3","Sassari":"1","Cagliari":"2","Monza e della Brianza":"4","Fermo":"5","Barletta-Andria-Trani":"2"}},"2020":{"I":{"Italia":"334"},"Z":{"Nord-ovest":"131","Isole":"18","Nord-est":"58","Centro":"68","Sud":"59"}}}