{"2012":{"I":{"Italia":"5821"}},"2013":{"I":{"Italia":"5750"}},"2014":{"I":{"Italia":"5645"}},"2015":{"I":{"Italia":"5628"}},"2016":{"I":{"Italia":"5812"}},"2017":{"I":{"Italia":"5678"}},"2018":{"I":{"Italia":"6279"}},"2019":{"I":{"Italia":"6317"},"Z":{"Nord-ovest":"655","Nord-est":"784","Isole":"1072","Centro":"1409","Sud":"2397"},"R":{"Piemonte":"189","Valle d'Aosta \/ Vall\u00e9e d'Aoste":"8","Liguria":"108","Lombardia":"350","Veneto":"282","Friuli-Venezia Giulia":"100","Emilia-Romagna":"303","Toscana":"220","Umbria":"118","Marche":"315","Lazio":"756","Abruzzo":"239","Molise":"31","Puglia":"758","Basilicata":"115","Campania":"893","Calabria":"361","Sicilia":"835","Sardegna":"237","Trentino Alto Adige \/ S\u00fcdtirol":"99","Provincia Autonoma Bolzano \/ Bozen":"46","Provincia Autonoma Trento":"53"},"P":{"Torino":"101","Vercelli":"4","Biella":"11","Verbano-Cusio-Ossola":"8","Novara":"13","Cuneo":"28","Asti":"9","Alessandria":"15","Valle d'Aosta \/ Vall\u00e9e d'Aoste":"8","Imperia":"13","Savona":"28","Genova":"50","La Spezia":"17","Varese":"22","Como":"20","Lecco":"10","Sondrio":"17","Milano":"96","Bergamo":"48","Brescia":"46","Pavia":"19","Lodi":"11","Cremona":"10","Mantova":"18","Bolzano \/ Bozen":"46","Trento":"53","Verona":"36","Vicenza":"46","Belluno":"13","Treviso":"57","Venezia":"57","Padova":"54","Rovigo":"19","Pordenone":"24","Udine":"39","Gorizia":"17","Trieste":"20","Piacenza":"16","Parma":"27","Reggio nell'Emilia":"52","Modena":"55","Bologna":"40","Ferrara":"25","Ravenna":"23","Forl\u00ec-Cesena":"34","Rimini":"31","Massa-Carrara":"18","Lucca":"25","Pistoia":"22","Firenze":"34","Prato":"11","Livorno":"26","Pisa":"24","Arezzo":"16","Siena":"20","Grosseto":"24","Perugia":"99","Terni":"19","Pesaro e Urbino":"46","Ancona":"122","Macerata":"55","Ascoli Piceno":"55","Viterbo":"49","Rieti":"19","Roma":"458","Latina":"105","Frosinone":"125","L'Aquila":"51","Teramo":"66","Pescara":"51","Chieti":"71","Isernia":"13","Campobasso":"18","Caserta":"181","Benevento":"62","Napoli":"403","Avellino":"66","Salerno":"181","Foggia":"113","Bari":"211","Taranto":"94","Brindisi":"85","Lecce":"195","Potenza":"74","Matera":"41","Cosenza":"156","Crotone":"44","Catanzaro":"48","Vibo Valentia":"28","Reggio di Calabria":"85","Trapani":"93","Palermo":"173","Messina":"120","Agrigento":"99","Caltanissetta":"45","Enna":"25","Catania":"156","Ragusa":"64","Siracusa":"60","Sassari":"68","Nuoro":"28","Cagliari":"57","Oristano":"36","Monza e della Brianza":"33","Fermo":"37","Barletta-Andria-Trani":"60","Sud Sardegna":"48"}},"2020":{"I":{"Italia":"6173"}}}