{"2012":{"I":{"Italia":"107213"}},"2013":{"I":{"Italia":"107801"}},"2014":{"I":{"Italia":"108156"}},"2015":{"I":{"Italia":"108432"}},"2016":{"I":{"Italia":"110981"}},"2017":{"I":{"Italia":"111099"}},"2018":{"I":{"Italia":"111655"}},"2019":{"I":{"Italia":"108863"},"Z":{"Nord-ovest":"30677","Nord-est":"21638","Centro":"23807","Sud":"23639","Isole":"9102"},"R":{"Piemonte":"6788","Liguria":"2878","Lombardia":"20782","Trentino Alto Adige \/ S\u00fcdtirol":"1712","Veneto":"9153","Friuli-Venezia Giulia":"1923","Emilia-Romagna":"8850","Umbria":"1503","Lazio":"11957","Abruzzo":"2709","Puglia":"6757","Campania":"10049","Basilicata":"810","Sicilia":"6762","Valle d'Aosta \/ Vall\u00e9e d'Aoste":"229","Sardegna":"2340","Toscana":"7313","Marche":"3034","Molise":"469","Calabria":"2845","Provincia Autonoma Bolzano \/ Bozen":"925","Provincia Autonoma Trento":"787"},"P":{"Torino":"3924","Vercelli":"196","Biella":"309","Verbano-Cusio-Ossola":"191","Novara":"556","Cuneo":"829","Asti":"202","Alessandria":"581","Valle d'Aosta \/ Vall\u00e9e d'Aoste":"229","Imperia":"391","Savona":"455","Genova":"1675","La Spezia":"357","Varese":"1487","Como":"1067","Lecco":"524","Sondrio":"254","Milano":"9246","Bergamo":"1930","Brescia":"2372","Pavia":"863","Lodi":"285","Cremona":"459","Mantova":"682","Bolzano \/ Bozen":"925","Trento":"787","Verona":"1759","Vicenza":"1809","Belluno":"229","Treviso":"1697","Venezia":"1392","Padova":"1941","Rovigo":"326","Pordenone":"486","Udine":"900","Gorizia":"179","Trieste":"358","Piacenza":"476","Parma":"952","Reggio nell'Emilia":"869","Modena":"1359","Bologna":"2705","Ferrara":"524","Ravenna":"568","Forl\u00ec-Cesena":"688","Rimini":"709","Massa-Carrara":"363","Lucca":"787","Pistoia":"564","Firenze":"2187","Prato":"691","Livorno":"505","Pisa":"801","Arezzo":"629","Siena":"478","Grosseto":"308","Perugia":"1143","Terni":"360","Pesaro e Urbino":"685","Ancona":"833","Macerata":"747","Ascoli Piceno":"376","Viterbo":"506","Rieti":"183","Roma":"9572","Latina":"982","Frosinone":"714","L'Aquila":"491","Teramo":"646","Pescara":"929","Chieti":"643","Isernia":"139","Campobasso":"330","Caserta":"1233","Benevento":"543","Napoli":"5505","Avellino":"692","Salerno":"2076","Foggia":"968","Bari":"2372","Taranto":"799","Brindisi":"547","Lecce":"1466","Potenza":"503","Matera":"307","Cosenza":"1097","Crotone":"253","Catanzaro":"576","Vibo Valentia":"189","Reggio di Calabria":"730","Trapani":"608","Palermo":"1606","Messina":"1041","Agrigento":"501","Caltanissetta":"320","Enna":"151","Catania":"1645","Ragusa":"384","Siracusa":"506","Sassari":"780","Nuoro":"218","Cagliari":"971","Oristano":"156","Monza e della Brianza":"1613","Fermo":"393","Barletta-Andria-Trani":"605","Sud Sardegna":"215"}},"2020":{"I":{"Italia":"112429"}}}