{"2012":{"I":{"Italia":"145"},"Z":{"Nord-est":"22","Isole":"28","Sud":"49","Nord-ovest":"21","Centro":"25"}},"2013":{"I":{"Italia":"149"},"Z":{"Nord-est":"21","Isole":"25","Sud":"54","Nord-ovest":"21","Centro":"28"}},"2014":{"I":{"Italia":"129"},"Z":{"Nord-est":"15","Isole":"23","Sud":"50","Nord-ovest":"19","Centro":"22"}},"2015":{"I":{"Italia":"131"},"Z":{"Nord-est":"15","Isole":"19","Sud":"53","Nord-ovest":"20","Centro":"24"}},"2016":{"I":{"Italia":"143"},"Z":{"Nord-est":"18","Isole":"24","Sud":"51","Nord-ovest":"24","Centro":"26"}},"2017":{"I":{"Italia":"134"},"Z":{"Nord-est":"18","Isole":"21","Sud":"47","Nord-ovest":"23","Centro":"25"}},"2018":{"I":{"Italia":"136"},"Z":{"Nord-est":"21","Isole":"21","Sud":"45","Nord-ovest":"26","Centro":"23"}},"2019":{"I":{"Italia":"128"},"Z":{"Nord-est":"19","Isole":"24","Sud":"39","Nord-ovest":"23","Centro":"23"},"R":{"Piemonte":"9","Lombardia":"14","Trentino Alto Adige \/ S\u00fcdtirol":"1","Friuli-Venezia Giulia":"2","Veneto":"9","Emilia-Romagna":"7","Toscana":"7","Umbria":"2","Marche":"2","Abruzzo":"4","Basilicata":"2","Puglia":"18","Calabria":"3","Campania":"12","Sicilia":"20","Sardegna":"4","Lazio":"12","Provincia Autonoma Bolzano \/ Bozen":"1"},"P":{"Torino":"1","Cuneo":"5","Asti":"2","Alessandria":"1","Como":"2","Milano":"3","Bergamo":"1","Brescia":"3","Pavia":"1","Cremona":"1","Mantova":"3","Bolzano \/ Bozen":"1","Verona":"5","Vicenza":"1","Treviso":"1","Rovigo":"2","Udine":"2","Parma":"2","Reggio nell'Emilia":"2","Modena":"1","Ferrara":"2","Lucca":"1","Firenze":"3","Arezzo":"1","Grosseto":"2","Perugia":"2","Ancona":"1","Viterbo":"1","Rieti":"2","Roma":"5","Latina":"3","Frosinone":"1","L'Aquila":"1","Pescara":"1","Chieti":"2","Caserta":"1","Benevento":"1","Avellino":"1","Salerno":"9","Foggia":"4","Bari":"2","Taranto":"3","Brindisi":"3","Lecce":"1","Matera":"2","Crotone":"1","Catanzaro":"2","Trapani":"4","Palermo":"1","Agrigento":"9","Caltanissetta":"1","Ragusa":"4","Siracusa":"1","Nuoro":"3","Fermo":"1","Barletta-Andria-Trani":"5","Sud Sardegna":"1"}},"2020":{"I":{"Italia":"121"},"Z":{"Nord-est":"18","Isole":"25","Sud":"40","Nord-ovest":"20","Centro":"18"}}}