{"2012":{"I":{"Italia":"26601"},"Z":{"Nord-ovest":"10120","Isole":"2011","Centro":"5498","Nord-est":"4738","Sud":"4234"}},"2013":{"I":{"Italia":"26772"},"Z":{"Nord-ovest":"10204","Isole":"2000","Centro":"5608","Nord-est":"4716","Sud":"4244"}},"2014":{"I":{"Italia":"27423"},"Z":{"Nord-ovest":"10543","Isole":"2000","Centro":"5674","Nord-est":"4829","Sud":"4377"}},"2015":{"I":{"Italia":"27415"},"Z":{"Nord-ovest":"10588","Isole":"1958","Centro":"5784","Nord-est":"4737","Sud":"4348"}},"2016":{"I":{"Italia":"28044"},"Z":{"Nord-ovest":"10910","Isole":"1963","Centro":"5885","Nord-est":"4805","Sud":"4481"}},"2017":{"I":{"Italia":"28364"},"Z":{"Nord-ovest":"11050","Isole":"2006","Centro":"5904","Nord-est":"4878","Sud":"4526"}},"2018":{"I":{"Italia":"28757"},"Z":{"Nord-ovest":"11179","Isole":"2082","Centro":"5939","Nord-est":"4942","Sud":"4615"}},"2019":{"I":{"Italia":"29028"},"Z":{"Nord-ovest":"11363","Isole":"2123","Centro":"5997","Nord-est":"4847","Sud":"4698"},"R":{"Piemonte":"2690","Valle d'Aosta \/ Vall\u00e9e d'Aoste":"87","Liguria":"1103","Lombardia":"7483","Trentino Alto Adige \/ S\u00fcdtirol":"461","Veneto":"1801","Friuli-Venezia Giulia":"400","Emilia-Romagna":"2185","Umbria":"310","Lazio":"3183","Abruzzo":"712","Campania":"1851","Puglia":"1440","Sicilia":"1477","Sardegna":"646","Toscana":"1790","Marche":"714","Molise":"107","Basilicata":"184","Calabria":"404","Provincia Autonoma Bolzano \/ Bozen":"264","Provincia Autonoma Trento":"197"},"P":{"Torino":"1709","Vercelli":"71","Biella":"84","Verbano-Cusio-Ossola":"59","Novara":"180","Cuneo":"237","Asti":"137","Alessandria":"213","Valle d'Aosta \/ Vall\u00e9e d'Aoste":"87","Imperia":"122","Savona":"186","Genova":"665","La Spezia":"130","Varese":"516","Como":"337","Lecco":"155","Sondrio":"77","Milano":"4032","Bergamo":"513","Brescia":"478","Pavia":"244","Lodi":"102","Cremona":"130","Mantova":"107","Bolzano \/ Bozen":"264","Trento":"197","Verona":"356","Vicenza":"293","Belluno":"49","Treviso":"241","Venezia":"343","Padova":"449","Rovigo":"70","Pordenone":"92","Udine":"148","Gorizia":"30","Trieste":"130","Piacenza":"109","Parma":"224","Reggio nell'Emilia":"161","Modena":"348","Bologna":"853","Ferrara":"114","Ravenna":"144","Forl\u00ec-Cesena":"106","Rimini":"126","Massa-Carrara":"86","Lucca":"115","Pistoia":"86","Firenze":"686","Prato":"170","Livorno":"199","Pisa":"156","Arezzo":"114","Siena":"72","Grosseto":"106","Perugia":"228","Terni":"82","Pesaro e Urbino":"137","Ancona":"209","Macerata":"153","Ascoli Piceno":"135","Viterbo":"80","Rieti":"54","Roma":"2699","Latina":"236","Frosinone":"114","L'Aquila":"132","Teramo":"172","Pescara":"225","Chieti":"183","Isernia":"33","Campobasso":"74","Caserta":"246","Benevento":"79","Napoli":"981","Avellino":"148","Salerno":"397","Foggia":"233","Bari":"482","Taranto":"204","Brindisi":"112","Lecce":"229","Potenza":"116","Matera":"68","Cosenza":"188","Crotone":"28","Catanzaro":"82","Vibo Valentia":"22","Reggio di Calabria":"84","Trapani":"91","Palermo":"385","Messina":"228","Agrigento":"90","Caltanissetta":"74","Enna":"48","Catania":"338","Ragusa":"82","Siracusa":"141","Sassari":"258","Nuoro":"41","Cagliari":"233","Oristano":"31","Monza e della Brianza":"792","Fermo":"80","Barletta-Andria-Trani":"180","Sud Sardegna":"83"}},"2020":{"I":{"Italia":"30660"},"Z":{"Nord-ovest":"12043","Isole":"2232","Centro":"6204","Nord-est":"5238","Sud":"4943"}}}