{"2012":{"I":{"Italia":"1750"},"Z":{"Centro":"317","Nord-ovest":"662","Isole":"95","Nord-est":"456","Sud":"220"}},"2013":{"I":{"Italia":"1800"},"Z":{"Centro":"333","Nord-ovest":"692","Isole":"85","Nord-est":"487","Sud":"203"}},"2014":{"I":{"Italia":"2028"},"Z":{"Centro":"352","Nord-ovest":"820","Isole":"81","Nord-est":"556","Sud":"219"}},"2015":{"I":{"Italia":"2171"},"Z":{"Centro":"381","Nord-ovest":"905","Isole":"80","Nord-est":"581","Sud":"224"}},"2016":{"I":{"Italia":"2383"},"Z":{"Centro":"395","Nord-ovest":"1039","Isole":"66","Nord-est":"676","Sud":"207"}},"2017":{"I":{"Italia":"2548"},"Z":{"Centro":"430","Nord-ovest":"1091","Isole":"73","Nord-est":"740","Sud":"214"}},"2018":{"I":{"Italia":"2685"},"Z":{"Centro":"470","Nord-ovest":"1100","Isole":"80","Nord-est":"813","Sud":"222"}},"2019":{"I":{"Italia":"3097"},"Z":{"Centro":"583","Nord-ovest":"1241","Isole":"94","Nord-est":"917","Sud":"262"},"R":{"Piemonte":"316","Valle d'Aosta \/ Vall\u00e9e d'Aoste":"11","Liguria":"66","Trentino Alto Adige \/ S\u00fcdtirol":"122","Emilia-Romagna":"338","Toscana":"222","Friuli-Venezia Giulia":"140","Umbria":"31","Marche":"64","Lazio":"266","Molise":"8","Campania":"102","Sicilia":"51","Basilicata":"14","Calabria":"31","Sardegna":"43","Lombardia":"848","Veneto":"317","Abruzzo":"33","Puglia":"74","Provincia Autonoma Bolzano \/ Bozen":"55","Provincia Autonoma Trento":"67"},"P":{"Torino":"205","Vercelli":"3","Biella":"12","Verbano-Cusio-Ossola":"13","Novara":"24","Cuneo":"34","Asti":"11","Alessandria":"14","Valle d'Aosta \/ Vall\u00e9e d'Aoste":"11","Imperia":"9","Savona":"17","Genova":"34","La Spezia":"6","Varese":"84","Como":"53","Lecco":"42","Sondrio":"12","Milano":"383","Bergamo":"73","Brescia":"56","Pavia":"31","Lodi":"9","Cremona":"25","Mantova":"23","Bolzano \/ Bozen":"55","Trento":"67","Verona":"80","Vicenza":"59","Belluno":"8","Treviso":"63","Venezia":"49","Padova":"54","Rovigo":"4","Pordenone":"30","Udine":"76","Gorizia":"12","Trieste":"22","Piacenza":"15","Parma":"30","Reggio nell'Emilia":"42","Modena":"58","Bologna":"105","Ferrara":"9","Ravenna":"41","Forl\u00ec-Cesena":"14","Rimini":"24","Massa-Carrara":"6","Lucca":"17","Pistoia":"16","Firenze":"88","Prato":"18","Livorno":"21","Pisa":"19","Arezzo":"16","Siena":"16","Grosseto":"5","Perugia":"30","Terni":"1","Pesaro e Urbino":"25","Ancona":"14","Macerata":"14","Ascoli Piceno":"9","Viterbo":"11","Rieti":"3","Roma":"228","Latina":"15","Frosinone":"9","L'Aquila":"11","Teramo":"4","Pescara":"11","Chieti":"7","Isernia":"2","Campobasso":"6","Caserta":"14","Benevento":"3","Napoli":"54","Avellino":"3","Salerno":"28","Foggia":"9","Bari":"32","Taranto":"6","Brindisi":"7","Lecce":"14","Potenza":"8","Matera":"6","Cosenza":"15","Crotone":"2","Catanzaro":"3","Vibo Valentia":"2","Reggio di Calabria":"9","Trapani":"4","Palermo":"16","Messina":"7","Agrigento":"2","Caltanissetta":"5","Enna":"1","Catania":"11","Ragusa":"2","Siracusa":"3","Sassari":"11","Nuoro":"6","Cagliari":"17","Oristano":"6","Monza e della Brianza":"57","Fermo":"2","Barletta-Andria-Trani":"6","Sud Sardegna":"3"}},"2020":{"I":{"Italia":"2915"},"Z":{"Centro":"559","Nord-ovest":"1162","Isole":"103","Nord-est":"850","Sud":"241"}}}