{"2012":{"I":{"Italia":"675"}},"2013":{"I":{"Italia":"688"}},"2014":{"I":{"Italia":"682"}},"2015":{"I":{"Italia":"690"}},"2016":{"I":{"Italia":"685"}},"2017":{"I":{"Italia":"658"}},"2018":{"I":{"Italia":"784"}},"2019":{"I":{"Italia":"6002"},"Z":{"Nord-ovest":"1673","Nord-est":"1092","Centro":"1373","Sud":"1273","Isole":"591"},"R":{"Valle d'Aosta \/ Vall\u00e9e d'Aoste":"7","Piemonte":"393","Lombardia":"1100","Veneto":"484","Friuli-Venezia Giulia":"136","Marche":"125","Toscana":"351","Umbria":"84","Lazio":"813","Abruzzo":"155","Campania":"501","Molise":"26","Basilicata":"48","Puglia":"372","Calabria":"171","Sardegna":"212","Liguria":"173","Trentino Alto Adige \/ S\u00fcdtirol":"80","Emilia-Romagna":"392","Sicilia":"379","Provincia Autonoma Trento":"39","Provincia Autonoma Bolzano \/ Bozen":"41"},"P":{"Torino":"231","Vercelli":"17","Biella":"16","Verbano-Cusio-Ossola":"16","Novara":"29","Cuneo":"29","Asti":"14","Alessandria":"41","Valle d'Aosta \/ Vall\u00e9e d'Aoste":"7","Imperia":"17","Savona":"17","Genova":"128","La Spezia":"11","Varese":"107","Como":"74","Lecco":"35","Sondrio":"15","Milano":"413","Bergamo":"94","Brescia":"121","Pavia":"48","Lodi":"16","Cremona":"30","Mantova":"32","Bolzano \/ Bozen":"41","Trento":"39","Verona":"131","Vicenza":"64","Belluno":"15","Treviso":"67","Venezia":"76","Padova":"100","Rovigo":"31","Pordenone":"29","Udine":"59","Gorizia":"21","Trieste":"27","Piacenza":"29","Parma":"30","Reggio nell'Emilia":"27","Modena":"61","Bologna":"117","Ferrara":"30","Ravenna":"22","Forl\u00ec-Cesena":"34","Rimini":"42","Massa-Carrara":"24","Lucca":"43","Pistoia":"25","Firenze":"107","Prato":"20","Livorno":"27","Pisa":"43","Arezzo":"32","Siena":"18","Grosseto":"12","Perugia":"67","Terni":"17","Pesaro e Urbino":"34","Ancona":"37","Macerata":"17","Ascoli Piceno":"19","Viterbo":"32","Rieti":"14","Roma":"658","Latina":"57","Frosinone":"52","L'Aquila":"44","Teramo":"35","Pescara":"39","Chieti":"37","Isernia":"9","Campobasso":"17","Caserta":"66","Benevento":"30","Napoli":"254","Avellino":"29","Salerno":"122","Foggia":"43","Bari":"122","Taranto":"57","Brindisi":"43","Lecce":"79","Potenza":"26","Matera":"22","Cosenza":"64","Crotone":"14","Catanzaro":"35","Vibo Valentia":"10","Reggio di Calabria":"48","Trapani":"35","Palermo":"107","Messina":"55","Agrigento":"32","Caltanissetta":"19","Enna":"11","Catania":"80","Ragusa":"16","Siracusa":"24","Sassari":"71","Nuoro":"21","Cagliari":"67","Oristano":"17","Monza e della Brianza":"115","Fermo":"18","Barletta-Andria-Trani":"28","Sud Sardegna":"36"}},"2020":{"I":{"Italia":"6926"}}}