{"2012":{"I":{"Italia":"3339"},"Z":{"Nord-ovest":"937","Isole":"345","Sud":"654","Centro":"671","Nord-est":"732"}},"2013":{"I":{"Italia":"3293"},"Z":{"Nord-ovest":"922","Isole":"337","Sud":"650","Centro":"672","Nord-est":"712"}},"2014":{"I":{"Italia":"3268"},"Z":{"Nord-ovest":"940","Isole":"319","Sud":"626","Centro":"667","Nord-est":"716"}},"2015":{"I":{"Italia":"3227"},"Z":{"Nord-ovest":"924","Isole":"316","Sud":"612","Centro":"663","Nord-est":"712"}},"2016":{"I":{"Italia":"3222"},"Z":{"Nord-ovest":"917","Isole":"331","Sud":"608","Centro":"655","Nord-est":"711"}},"2017":{"I":{"Italia":"3204"},"Z":{"Nord-ovest":"930","Isole":"325","Sud":"589","Centro":"638","Nord-est":"722"}},"2018":{"I":{"Italia":"3157"},"Z":{"Nord-ovest":"902","Isole":"325","Sud":"592","Centro":"635","Nord-est":"703"}},"2019":{"I":{"Italia":"3084"},"Z":{"Nord-ovest":"893","Isole":"304","Sud":"580","Centro":"631","Nord-est":"676"},"R":{"Piemonte":"226","Lombardia":"559","Liguria":"103","Friuli-Venezia Giulia":"60","Trentino Alto Adige \/ S\u00fcdtirol":"41","Veneto":"290","Umbria":"56","Emilia-Romagna":"285","Marche":"90","Campania":"169","Abruzzo":"73","Puglia":"218","Molise":"16","Basilicata":"21","Sardegna":"81","Sicilia":"223","Valle d'Aosta \/ Vall\u00e9e d'Aoste":"5","Toscana":"196","Lazio":"289","Calabria":"83","Provincia Autonoma Bolzano \/ Bozen":"16","Provincia Autonoma Trento":"25"},"P":{"Torino":"122","Vercelli":"5","Biella":"15","Verbano-Cusio-Ossola":"6","Novara":"17","Cuneo":"25","Asti":"19","Alessandria":"17","Valle d'Aosta \/ Vall\u00e9e d'Aoste":"5","Imperia":"20","Savona":"26","Genova":"44","La Spezia":"13","Varese":"56","Como":"35","Lecco":"15","Sondrio":"5","Milano":"159","Bergamo":"65","Brescia":"76","Pavia":"26","Lodi":"14","Cremona":"23","Mantova":"27","Bolzano \/ Bozen":"16","Trento":"25","Verona":"65","Vicenza":"56","Belluno":"7","Treviso":"39","Venezia":"42","Padova":"66","Rovigo":"15","Pordenone":"13","Udine":"31","Gorizia":"4","Trieste":"12","Piacenza":"14","Parma":"20","Reggio nell'Emilia":"40","Modena":"50","Bologna":"67","Ferrara":"29","Ravenna":"23","Forl\u00ec-Cesena":"26","Rimini":"16","Massa-Carrara":"7","Lucca":"31","Pistoia":"19","Firenze":"40","Prato":"8","Livorno":"20","Pisa":"23","Arezzo":"14","Siena":"20","Grosseto":"14","Perugia":"42","Terni":"14","Pesaro e Urbino":"20","Ancona":"24","Macerata":"20","Ascoli Piceno":"11","Viterbo":"18","Rieti":"3","Roma":"199","Latina":"47","Frosinone":"22","L'Aquila":"19","Teramo":"19","Pescara":"21","Chieti":"14","Isernia":"4","Campobasso":"12","Caserta":"20","Benevento":"9","Napoli":"85","Avellino":"9","Salerno":"46","Foggia":"25","Bari":"54","Taranto":"17","Brindisi":"27","Lecce":"71","Potenza":"12","Matera":"9","Cosenza":"35","Crotone":"7","Catanzaro":"22","Vibo Valentia":"3","Reggio di Calabria":"16","Trapani":"33","Palermo":"38","Messina":"33","Agrigento":"18","Caltanissetta":"17","Enna":"12","Catania":"33","Ragusa":"27","Siracusa":"12","Sassari":"26","Nuoro":"13","Cagliari":"24","Oristano":"7","Monza e della Brianza":"58","Fermo":"15","Barletta-Andria-Trani":"24","Sud Sardegna":"11"}},"2020":{"I":{"Italia":"3145"},"Z":{"Nord-ovest":"913","Isole":"299","Sud":"600","Centro":"646","Nord-est":"687"}}}