{"2012":{"I":{"Italia":"5536"}},"2013":{"I":{"Italia":"5500"}},"2014":{"I":{"Italia":"5486"}},"2015":{"I":{"Italia":"5263"}},"2016":{"I":{"Italia":"5288"}},"2017":{"I":{"Italia":"5316"}},"2018":{"I":{"Italia":"3934"}},"2019":{"I":{"Italia":"3257"},"Z":{"Nord-ovest":"1260","Nord-est":"892","Centro":"609","Sud":"368","Isole":"128"},"R":{"Valle d'Aosta \/ Vall\u00e9e d'Aoste":"12","Piemonte":"280","Lombardia":"874","Veneto":"336","Friuli-Venezia Giulia":"172","Emilia-Romagna":"289","Lazio":"247","Toscana":"221","Umbria":"45","Marche":"96","Abruzzo":"50","Molise":"6","Basilicata":"13","Puglia":"109","Calabria":"32","Sicilia":"83","Sardegna":"45","Liguria":"94","Trentino Alto Adige \/ S\u00fcdtirol":"95","Campania":"158","Provincia Autonoma Bolzano \/ Bozen":"47","Provincia Autonoma Trento":"48"},"P":{"Torino":"138","Vercelli":"10","Biella":"15","Verbano-Cusio-Ossola":"19","Novara":"26","Cuneo":"40","Asti":"6","Alessandria":"26","Valle d'Aosta \/ Vall\u00e9e d'Aoste":"12","Imperia":"14","Savona":"14","Genova":"57","La Spezia":"9","Varese":"52","Como":"52","Lecco":"26","Sondrio":"10","Milano":"358","Bergamo":"82","Brescia":"117","Pavia":"35","Lodi":"11","Cremona":"23","Mantova":"29","Bolzano \/ Bozen":"47","Trento":"48","Verona":"85","Vicenza":"66","Belluno":"8","Treviso":"53","Venezia":"47","Padova":"62","Rovigo":"15","Pordenone":"29","Udine":"84","Gorizia":"22","Trieste":"37","Piacenza":"24","Parma":"26","Reggio nell'Emilia":"23","Modena":"41","Bologna":"87","Ferrara":"5","Ravenna":"31","Forl\u00ec-Cesena":"22","Rimini":"30","Massa-Carrara":"18","Lucca":"15","Pistoia":"17","Firenze":"63","Prato":"25","Livorno":"21","Pisa":"21","Arezzo":"16","Siena":"16","Grosseto":"9","Perugia":"35","Terni":"10","Pesaro e Urbino":"24","Ancona":"29","Macerata":"19","Ascoli Piceno":"13","Viterbo":"10","Rieti":"3","Roma":"207","Latina":"17","Frosinone":"10","L'Aquila":"11","Teramo":"18","Pescara":"16","Chieti":"5","Isernia":"3","Campobasso":"3","Caserta":"21","Benevento":"7","Napoli":"102","Avellino":"8","Salerno":"20","Foggia":"22","Bari":"43","Taranto":"11","Brindisi":"4","Lecce":"15","Potenza":"8","Matera":"5","Cosenza":"14","Crotone":"3","Catanzaro":"9","Reggio di Calabria":"6","Trapani":"5","Palermo":"25","Messina":"9","Agrigento":"11","Caltanissetta":"2","Catania":"17","Ragusa":"8","Siracusa":"6","Sassari":"15","Nuoro":"5","Cagliari":"19","Oristano":"2","Monza e della Brianza":"79","Fermo":"11","Barletta-Andria-Trani":"14","Sud Sardegna":"4"}},"2020":{"I":{"Italia":"3003"}}}